rune/__init__.py
rune/discovery.py
rune/exceptions.py
rune/group.py
rune/loader.py
rune/py.typed
rune/tools/__init__.py
rune/tools/console.py
rune_lib-0.0.4.dist-info/METADATA
rune_lib-0.0.4.dist-info/WHEEL
rune_lib-0.0.4.dist-info/licenses/LICENSE
rune_lib-0.0.4.dist-info/RECORD
