Metadata-Version: 2.4
Name: rune-lib
Version: 0.0.4
Summary: Zero-configuration, OS-independent asset management for Python
Project-URL: Homepage, https://github.com/Yrrrrrf/manifold
Project-URL: Repository, https://github.com/Yrrrrrf/manifold
Author-email: Yrrrrrf <fer.rezac@outlook.com>
License: MIT
License-File: LICENSE
Keywords: assets,developer-tools,path-management,pathlib,resources,utility
Classifier: Development Status :: 2 - Pre-Alpha
Classifier: Intended Audience :: Developers
Classifier: License :: OSI Approved :: MIT License
Classifier: Operating System :: OS Independent
Classifier: Programming Language :: Python :: 3.10
Classifier: Programming Language :: Python :: 3.11
Classifier: Programming Language :: Python :: 3.12
Classifier: Programming Language :: Python :: 3.13
Classifier: Topic :: Software Development :: Libraries :: Python Modules
Classifier: Topic :: Utilities
Classifier: Typing :: Typed
Requires-Python: >=3.10
Requires-Dist: rich>=14.1.0
